{
    "errorCode": "100",
    "message": "获取成功",
    "data": [{
            "id": 1,
            "studentId": "2017",
            "gender": 0,
            "name": "1"
        },
        {
            "id": 2,
            "studentId": "2017",
            "gender": 0,
            "name": "1"
        }, {
            "id": 3,
            "studentId": "2017",
            "gender": 0,
            "name": "2"
        }, {
            "id": 4,
            "studentId": "2017",
            "gender": 0,
            "name": "2"
        }
    ]
}